{
  "title": "1.Upload pricing schedules and other documents",
  "subtitle": "[ Description for this page ]",
  "description": "",
  "taskList": [
    {
      "title": "Upload your pricing schedule (attachment 4)",
      "hreftitle": "Add / edit link",
      "href": "/ca/upload-pricing"
    },
    {
      "title": "Upload any additional document (optional)",
      "hreftitle": "Add / edit link",
      "href": "/ca/upload-supporting-doc"
    }
  ],
  "backJump": {
    "title": "Return to Write and publish your requirements",
    "href": "/ca/task-list"
  }
}
