{
  "breadCrumbs": [
    {
      "text": "Dashboard",
      "href": "/dashboard"
    },
    {
      "text": "Choose a commercial agreement",
      "href": "/projects/choose-agreement"
    },
    {
      "text": "Procurement overview",
      "href": "/projects/create-or-choose"
    },
    {
      "text": "Write and publish your requirements",
      "href": "#"
    }
  ],

  "title": "Write and publish your requirements for stage 2",
  "subtitle": null,
  "events": [
    {
      "eventno": 1,
      "eventTitle": "Project and collaborators",
      "eventTask": [
        {
          "Task": 1,
          "link": "/rfp/name-your-project",
          "title": "Name your project",
          "required": "mandatory",
          "status": "Optional"
        },
        {
          "Task": 2,
          "link": "/rfp/procurement-lead",
          "title": "Change who will lead your project",
          "required": "optional",
          "status": "Optional"
        },
        {
          "Task": 3,
          "link": "/rfp/add-collaborators",
          "title": "Add members to your project",
          "required": "optional",
          "status": "Optional"
        }
      ]
    },
    {
      "eventno": 2,
      "eventTitle": "Upload pricing schedules and other documents",
      "eventTask": [
        {
          "Task": 1,
          "title": " Upload your pricing schedule",
          "required": "optional",
          "status": "Todo",
          "link": "/rfp/upload-attachment"
        },
        {
          "Task": 2,
          "title": "Upload your core terms, call-off order form and schedules (terms and conditions) ",
          "required": "optional",
          "link": "/rfp/upload-doc",
          "status": "Cannot start yet"
        },
        {
          "Task": 3,
          "title": " Upload assessment documents",
          "required": "optional",
          "status": "Cannot start yet",
          "link": "/rfp/upload-additional"
        }
      ]
    },
    {
      "eventno": 3,
      "eventTitle": "Review and publish stage 2: further assessment",
      "eventTask": [
        {
          "Task": 1,
          "title": "Set your timeline",
          "required": "mandatory",
          "status": "Cannot start yet",
          "link": "/rfp/response-date"
        },
        {
          "Task": 2,
          "title": "Review and publish stage 2",
          "required": "mandatory",
          "status": "Cannot start yet",
          "link": "/rfp/review"
        }
      ]
    }
  ],
  "form": {
    "backJump": {
      "title": "Return to procurement overview",
      "href": "/projects/create-or-choose"
    }
  }
}
