{
    "breadCrumbs": [{
            "text": "Dashboard",
            "href": "/dashboard"
        },
        {
            "text": "Choose a commercial agreement",
            "href": "/projects/choose-agreement"
        },
        {
            "text": "Procurement overview",
            "href": "/projects/create-or-choose"
        },
        {
            "text": "Write and publish your requirements",
            "href": "/rfp/task-list"
        },
        {
            "text": "Upload your pricing schedule and other documents",
            "href": "upload"
        },
        {
            "text": "Upload your pricing schedule",
            "href": "#"
        }
    ],

    "title": "Upload your pricing schedule",
    "subtitle1": "Upload your pricing schedule at the bottom of the screen. Please name the document 'Attachment 4'.",
    "subtitle2": "Include what pricing model you expect suppliers to provide.",
    "subtitle3": "You can upload any other supporting documents in the pages that follow.",
    "subtitle_4":"Include what pricing model you expect the supplier to provide.",
    "filedesc": "You can upload 1 file no larger than 300MB. Acceptable file formats: csv, doc, docx, jpg, kml, ods, odt, pdf, png, ppt, pptx, rdf, rtf, txt, xls, xlsx, xml, zip",
    "backJump": {
        "title": "Write and publish your requirements",
        "href": "/rfp/task-list"
    },
    "template": []
}